straico/__init__.py
straico/client.py
straico/straico.py
straico-1.0.2.dist-info/METADATA
straico-1.0.2.dist-info/WHEEL
straico-1.0.2.dist-info/top_level.txt
straico-1.0.2.dist-info/RECORD
