Metadata-Version: 2.1
Name: straico
Version: 1.0.2
Summary: Unofficial implementation of https://documenter.getpostman.com/view/5900072/2s9YyzddrR
Home-page: UNKNOWN
Author: Stephen
Author-email: stephen@mgclabs.com
License: UNKNOWN
Platform: UNKNOWN
Requires-Dist: requests
